[
	{
		"name": "adult-LGAN-v-1hot-gmm-noKL",
		"train": "dataset/adult_train.csv",
		"sample": "dataset/adult_train.csv",	
		"normalize_cols":[],
		"gmm_cols":[0,2,4,10,11,12],
		"one-hot_cols":[1,3,5,6,7,8,9,13],
		"ordinal_cols":[],
		"model": "LGAN",
		"n_epochs": 5,
		"steps_per_epoch": 10000,
		"n_search": 7,
		"rand_search": "no",
		"param":{"batch_size":256, "z_dim":128, "gen_feature_dim":400, "gen_lstm_dim":300, "dis_hidden_dim": 300, "dis_num_layers":2, "lr":0.0001},
		"train_method":"VTrain",
		"KL":"no"
	},
	{
		"name": "adult-LGAN-w-1hot-gmm-noKL",
		"train": "dataset/adult_train.csv",
		"sample": "dataset/adult_train.csv",	
		"normalize_cols":[],
		"gmm_cols":[0,2,4,10,11,12],
		"one-hot_cols":[1,3,5,6,7,8,9,13],
		"ordinal_cols":[],
		"model": "LGAN",
		"nd": 5,
		"ng": 10000,
		"n_search": 7,
		"rand_search": "no",
		"param":{"batch_size":256, "z_dim":128, "gen_feature_dim":400, "gen_lstm_dim":300, "dis_hidden_dim": 300, "dis_num_layers":2, "lr":0.0001},
		"train_method":"WTrain",
		"KL":"no"
	},
	{
		"name": "adult-LGAN-w-1hot-gmm",
		"train": "dataset/adult_train.csv",
		"sample": "dataset/adult_train.csv",	
		"normalize_cols":[],
		"gmm_cols":[0,2,4,10,11,12],
		"one-hot_cols":[1,3,5,6,7,8,9,13],
		"ordinal_cols":[],
		"model": "LGAN",
		"nd": 5,
		"ng": 10000,
		"n_search": 7,
		"rand_search": "no",
		"param":{"batch_size":256, "z_dim":128, "gen_feature_dim":400, "gen_lstm_dim":300, "dis_hidden_dim": 300, "dis_num_layers":2, "lr":0.0001},
		"train_method":"WTrain"
	}
]
